deep_train/__init__.py
deep_train/common/__init__.py
deep_train/common/constants.py
deep_train/common/utils.py
deep_train/pytorch/__init__.py
deep_train/pytorch/checkpointer.py
deep_train/pytorch/contexts.py
deep_train/pytorch/reproducibility.py
deep_train/pytorch/tasks/__init__.py
deep_train/pytorch/tasks/base_task.py
deep_train/pytorch/tasks/sequence_classification_task.py
deep_train/pytorch/trainer.py
deep_train-0.1.1a4.dist-info/WHEEL
deep_train-0.1.1a4.dist-info/METADATA
deep_train-0.1.1a4.dist-info/RECORD
